{
    "submit_type_id_statistic": {
        "RECORD": [],
        "DOCUMENT": [
            "1"
        ],
        "ACTION": [
            "2",
            "3",
            "4"
        ],
        "ROOT": [
            "0"
        ]
    },
    "delete_id": [
        "0"
    ],
    "all_id": [
        "0",
        "1",
        "2",
        "3",
        "4"
    ],
    "submit_time": {
        "0": "",
        "1": "year:2023||month:11||day:22||hour:19||minute:1||second:1",
        "2": "year:2023||month:11||day:22||hour:19||minute:6||second:22",
        "3": "year:2023||month:11||day:22||hour:19||minute:11||second:2",
        "4": "year:2023||month:11||day:22||hour:19||minute:12||second:44"
    },
    "submit_type": {
        "1": "DOCUMENT",
        "2": "ACTION",
        "3": "ACTION",
        "4": "ACTION"
    }
}